S3Storage.py
setup.py
django_simple_s3storage.egg-info/PKG-INFO
django_simple_s3storage.egg-info/SOURCES.txt
django_simple_s3storage.egg-info/dependency_links.txt
django_simple_s3storage.egg-info/not-zip-safe
django_simple_s3storage.egg-info/requires.txt
django_simple_s3storage.egg-info/top_level.txt