Metadata-Version: 1.0
Name: django-simple-s3storage
Version: 0.1
Summary: A simple django storage backend for Amazon S3 built ontop of Boto.
Home-page: http://www.kaelten.com/django-simple-s3storage
Author: Bryan McLemore
Author-email: kaelten@gmail.com
License: BSD
Platform: UNKNOWN
Classifier: Development Status :: 4 - Beta
Classifier: Environment :: Web Environment
Classifier: Intended Audience :: Developers
Classifier: License :: OSI Approved :: BSD License
Classifier: Operating System :: OS Independent
Classifier: Programming Language :: Python
Classifier: Framework :: Django
